<annotation verified="yes">
	<folder>all_in_one_v6_Back</folder>
	<filename>CamBack_20211029_110343.jpg</filename>
	<path>C:\Users\tianchu.wang\Desktop\all_in_one_v6\all_in_one_v6_Back\CamBack_20211029_110343.jpg</path>
	<source>
		<database>Unknown</database>
	</source>
	<size>
		<width>1936</width>
		<height>1216</height>
		<depth>1</depth>
	</size>
	<segmented>0</segmented>
	<object>
		<name>Schraube</name>
		<pose>Unspecified</pose>
		<truncated>0</truncated>
		<difficult>0</difficult>
		<bndbox>
			<xmin>524</xmin>
			<ymin>451</ymin>
			<xmax>563</xmax>
			<ymax>491</ymax>
		</bndbox>
	</object>
	<object>
		<name>Schraube</name>
		<pose>Unspecified</pose>
		<truncated>0</truncated>
		<difficult>0</difficult>
		<bndbox>
			<xmin>544</xmin>
			<ymin>644</ymin>
			<xmax>583</xmax>
			<ymax>684</ymax>
		</bndbox>
	</object>
	<object>
		<name>Schraube</name>
		<pose>Unspecified</pose>
		<truncated>0</truncated>
		<difficult>0</difficult>
		<bndbox>
			<xmin>1361</xmin>
			<ymin>649</ymin>
			<xmax>1400</xmax>
			<ymax>689</ymax>
		</bndbox>
	</object>
	<object>
		<name>Schraube</name>
		<pose>Unspecified</pose>
		<truncated>0</truncated>
		<difficult>0</difficult>
		<bndbox>
			<xmin>1383</xmin>
			<ymin>453</ymin>
			<xmax>1422</xmax>
			<ymax>493</ymax>
		</bndbox>
	</object>
	<object>
		<name>Schraube_gespiegelt</name>
		<pose>Unspecified</pose>
		<truncated>0</truncated>
		<difficult>0</difficult>
		<bndbox>
			<xmin>545</xmin>
			<ymin>714</ymin>
			<xmax>591</xmax>
			<ymax>772</ymax>
		</bndbox>
	</object>
	<object>
		<name>Schraube_gespiegelt</name>
		<pose>Unspecified</pose>
		<truncated>0</truncated>
		<difficult>0</difficult>
		<bndbox>
			<xmin>1357</xmin>
			<ymin>717</ymin>
			<xmax>1401</xmax>
			<ymax>778</ymax>
		</bndbox>
	</object>
	<object>
		<name>Schraube_gespiegelt</name>
		<pose>Unspecified</pose>
		<truncated>0</truncated>
		<difficult>0</difficult>
		<bndbox>
			<xmin>530</xmin>
			<ymin>905</ymin>
			<xmax>578</xmax>
			<ymax>964</ymax>
		</bndbox>
	</object>
	<object>
		<name>Schraube_gespiegelt</name>
		<pose>Unspecified</pose>
		<truncated>0</truncated>
		<difficult>0</difficult>
		<bndbox>
			<xmin>1373</xmin>
			<ymin>905</ymin>
			<xmax>1413</xmax>
			<ymax>973</ymax>
		</bndbox>
	</object>
	<object>
		<name>CamBack</name>
		<pose>Unspecified</pose>
		<truncated>0</truncated>
		<difficult>0</difficult>
		<bndbox>
			<xmin>361</xmin>
			<ymin>426</ymin>
			<xmax>1548</xmax>
			<ymax>705</ymax>
		</bndbox>
	</object>
</annotation>
