<annotation>
	<folder>Bilder_webcam_ipevo_20220516</folder>
	<filename>IPEVO_CamTop_17.jpg</filename>
	<path>C:\Users\tianchu.wang\Desktop\Bilder_webcam_ipevo_20220516\IPEVO_CamTop_17.jpg</path>
	<source>
		<database>Unknown</database>
	</source>
	<size>
		<width>3264</width>
		<height>2448</height>
		<depth>3</depth>
	</size>
	<segmented>0</segmented>
	<object>
		<name>Schraube</name>
		<pose>Unspecified</pose>
		<truncated>0</truncated>
		<difficult>0</difficult>
		<bndbox>
			<xmin>374</xmin>
			<ymin>1673</ymin>
			<xmax>474</xmax>
			<ymax>1773</ymax>
		</bndbox>
	</object>
	<object>
		<name>Schraube</name>
		<pose>Unspecified</pose>
		<truncated>0</truncated>
		<difficult>0</difficult>
		<bndbox>
			<xmin>1662</xmin>
			<ymin>767</ymin>
			<xmax>1762</xmax>
			<ymax>870</ymax>
		</bndbox>
	</object>
	<object>
		<name>Schraube</name>
		<pose>Unspecified</pose>
		<truncated>0</truncated>
		<difficult>0</difficult>
		<bndbox>
			<xmin>2712</xmin>
			<ymin>679</ymin>
			<xmax>2821</xmax>
			<ymax>788</ymax>
		</bndbox>
	</object>
	<object>
		<name>Schraube</name>
		<pose>Unspecified</pose>
		<truncated>0</truncated>
		<difficult>0</difficult>
		<bndbox>
			<xmin>2189</xmin>
			<ymin>412</ymin>
			<xmax>2289</xmax>
			<ymax>512</ymax>
		</bndbox>
	</object>
	<object>
		<name>Schraube</name>
		<pose>Unspecified</pose>
		<truncated>0</truncated>
		<difficult>0</difficult>
		<bndbox>
			<xmin>2289</xmin>
			<ymin>759</ymin>
			<xmax>2392</xmax>
			<ymax>862</ymax>
		</bndbox>
	</object>
	<object>
		<name>Schraube</name>
		<pose>Unspecified</pose>
		<truncated>0</truncated>
		<difficult>0</difficult>
		<bndbox>
			<xmin>2295</xmin>
			<ymin>1773</ymin>
			<xmax>2406</xmax>
			<ymax>1873</ymax>
		</bndbox>
	</object>
	<object>
		<name>Schraube</name>
		<pose>Unspecified</pose>
		<truncated>0</truncated>
		<difficult>0</difficult>
		<bndbox>
			<xmin>1677</xmin>
			<ymin>1773</ymin>
			<xmax>1777</xmax>
			<ymax>1879</ymax>
		</bndbox>
	</object>
	<object>
		<name>Schraube_halb</name>
		<pose>Unspecified</pose>
		<truncated>0</truncated>
		<difficult>0</difficult>
		<bndbox>
			<xmin>356</xmin>
			<ymin>715</ymin>
			<xmax>459</xmax>
			<ymax>817</ymax>
		</bndbox>
	</object>
	<object>
		<name>Schraube_halb</name>
		<pose>Unspecified</pose>
		<truncated>0</truncated>
		<difficult>0</difficult>
		<bndbox>
			<xmin>862</xmin>
			<ymin>426</ymin>
			<xmax>965</xmax>
			<ymax>535</ymax>
		</bndbox>
	</object>
	<object>
		<name>Schraube_halb</name>
		<pose>Unspecified</pose>
		<truncated>0</truncated>
		<difficult>0</difficult>
		<bndbox>
			<xmin>886</xmin>
			<ymin>1944</ymin>
			<xmax>992</xmax>
			<ymax>2044</ymax>
		</bndbox>
	</object>
	<object>
		<name>Schraube_halb</name>
		<pose>Unspecified</pose>
		<truncated>0</truncated>
		<difficult>0</difficult>
		<bndbox>
			<xmin>2200</xmin>
			<ymin>1932</ymin>
			<xmax>2309</xmax>
			<ymax>2032</ymax>
		</bndbox>
	</object>
	<object>
		<name>Schraube_halb</name>
		<pose>Unspecified</pose>
		<truncated>0</truncated>
		<difficult>0</difficult>
		<bndbox>
			<xmin>2718</xmin>
			<ymin>1647</ymin>
			<xmax>2824</xmax>
			<ymax>1753</ymax>
		</bndbox>
	</object>
	<object>
		<name>Loch_Montage</name>
		<pose>Unspecified</pose>
		<truncated>0</truncated>
		<difficult>0</difficult>
		<bndbox>
			<xmin>974</xmin>
			<ymin>785</ymin>
			<xmax>1050</xmax>
			<ymax>870</ymax>
		</bndbox>
	</object>
	<object>
		<name>Loch_Montage</name>
		<pose>Unspecified</pose>
		<truncated>0</truncated>
		<difficult>0</difficult>
		<bndbox>
			<xmin>1983</xmin>
			<ymin>767</ymin>
			<xmax>2062</xmax>
			<ymax>853</ymax>
		</bndbox>
	</object>
	<object>
		<name>LOGO_Kontron_font</name>
		<pose>Unspecified</pose>
		<truncated>0</truncated>
		<difficult>0</difficult>
		<bndbox>
			<xmin>1568</xmin>
			<ymin>1173</ymin>
			<xmax>1865</xmax>
			<ymax>1265</ymax>
		</bndbox>
	</object>
	<object>
		<name>Barcode</name>
		<pose>Unspecified</pose>
		<truncated>0</truncated>
		<difficult>0</difficult>
		<bndbox>
			<xmin>1630</xmin>
			<ymin>1582</ymin>
			<xmax>1921</xmax>
			<ymax>1667</ymax>
		</bndbox>
	</object>
	<object>
		<name>Barcode</name>
		<pose>Unspecified</pose>
		<truncated>0</truncated>
		<difficult>0</difficult>
		<bndbox>
			<xmin>1965</xmin>
			<ymin>1582</ymin>
			<xmax>2239</xmax>
			<ymax>1667</ymax>
		</bndbox>
	</object>
	<object>
		<name>Label_Seriennummer</name>
		<pose>Unspecified</pose>
		<truncated>0</truncated>
		<difficult>0</difficult>
		<bndbox>
			<xmin>1500</xmin>
			<ymin>1097</ymin>
			<xmax>2300</xmax>
			<ymax>1753</ymax>
		</bndbox>
	</object>
	<object>
		<name>CamTop</name>
		<pose>Unspecified</pose>
		<truncated>0</truncated>
		<difficult>0</difficult>
		<bndbox>
			<xmin>277</xmin>
			<ymin>323</ymin>
			<xmax>2915</xmax>
			<ymax>2123</ymax>
		</bndbox>
	</object>
</annotation>
