<annotation verified="yes">
	<folder>Bilder_webcam_ipevo_20220516</folder>
	<filename>IPEVO_CamFront_1.jpg</filename>
	<path>C:\Users\tianchu.wang\Desktop\Bilder_webcam_ipevo_20220516\IPEVO_CamFront_1.jpg</path>
	<source>
		<database>Unknown</database>
	</source>
	<size>
		<width>1920</width>
		<height>1080</height>
		<depth>3</depth>
	</size>
	<segmented>0</segmented>
	<object>
		<name>Schraube_halb</name>
		<pose>Unspecified</pose>
		<truncated>0</truncated>
		<difficult>0</difficult>
		<bndbox>
			<xmin>246</xmin>
			<ymin>116</ymin>
			<xmax>315</xmax>
			<ymax>183</ymax>
		</bndbox>
	</object>
	<object>
		<name>Schraube</name>
		<pose>Unspecified</pose>
		<truncated>0</truncated>
		<difficult>0</difficult>
		<bndbox>
			<xmin>1836</xmin>
			<ymin>143</ymin>
			<xmax>1895</xmax>
			<ymax>209</ymax>
		</bndbox>
	</object>
	<object>
		<name>Schraube</name>
		<pose>Unspecified</pose>
		<truncated>0</truncated>
		<difficult>0</difficult>
		<bndbox>
			<xmin>296</xmin>
			<ymin>478</ymin>
			<xmax>362</xmax>
			<ymax>545</ymax>
		</bndbox>
	</object>
	<object>
		<name>Schraube_halb</name>
		<pose>Unspecified</pose>
		<truncated>0</truncated>
		<difficult>0</difficult>
		<bndbox>
			<xmin>1779</xmin>
			<ymin>495</ymin>
			<xmax>1843</xmax>
			<ymax>562</ymax>
		</bndbox>
	</object>
	<object>
		<name>Schraube_rund</name>
		<pose>Unspecified</pose>
		<truncated>0</truncated>
		<difficult>0</difficult>
		<bndbox>
			<xmin>327</xmin>
			<ymin>195</ymin>
			<xmax>388</xmax>
			<ymax>259</ymax>
		</bndbox>
	</object>
	<object>
		<name>Schraube_rund</name>
		<pose>Unspecified</pose>
		<truncated>0</truncated>
		<difficult>0</difficult>
		<bndbox>
			<xmin>894</xmin>
			<ymin>207</ymin>
			<xmax>955</xmax>
			<ymax>271</ymax>
		</bndbox>
	</object>
	<object>
		<name>Schraube_rund</name>
		<pose>Unspecified</pose>
		<truncated>0</truncated>
		<difficult>0</difficult>
		<bndbox>
			<xmin>693</xmin>
			<ymin>201</ymin>
			<xmax>754</xmax>
			<ymax>265</ymax>
		</bndbox>
	</object>
	<object>
		<name>Schraube_rund</name>
		<pose>Unspecified</pose>
		<truncated>0</truncated>
		<difficult>0</difficult>
		<bndbox>
			<xmin>533</xmin>
			<ymin>196</ymin>
			<xmax>594</xmax>
			<ymax>260</ymax>
		</bndbox>
	</object>
	<object>
		<name>LED_HDD</name>
		<pose>Unspecified</pose>
		<truncated>0</truncated>
		<difficult>0</difficult>
		<bndbox>
			<xmin>362</xmin>
			<ymin>298</ymin>
			<xmax>422</xmax>
			<ymax>383</ymax>
		</bndbox>
	</object>
	<object>
		<name>LED_PWR</name>
		<pose>Unspecified</pose>
		<truncated>0</truncated>
		<difficult>0</difficult>
		<bndbox>
			<xmin>362</xmin>
			<ymin>381</ymin>
			<xmax>427</xmax>
			<ymax>460</ymax>
		</bndbox>
	</object>
	<object>
		<name>Reset_button</name>
		<pose>Unspecified</pose>
		<truncated>0</truncated>
		<difficult>0</difficult>
		<bndbox>
			<xmin>426</xmin>
			<ymin>367</ymin>
			<xmax>486</xmax>
			<ymax>464</ymax>
		</bndbox>
	</object>
	<object>
		<name>Display_Port</name>
		<pose>Unspecified</pose>
		<truncated>0</truncated>
		<difficult>0</difficult>
		<bndbox>
			<xmin>515</xmin>
			<ymin>366</ymin>
			<xmax>679</xmax>
			<ymax>434</ymax>
		</bndbox>
	</object>
	<object>
		<name>Schraube_abstand</name>
		<pose>Unspecified</pose>
		<truncated>0</truncated>
		<difficult>0</difficult>
		<bndbox>
			<xmin>691</xmin>
			<ymin>347</ymin>
			<xmax>745</xmax>
			<ymax>409</ymax>
		</bndbox>
	</object>
	<object>
		<name>Schraube_abstand</name>
		<pose>Unspecified</pose>
		<truncated>0</truncated>
		<difficult>0</difficult>
		<bndbox>
			<xmin>896</xmin>
			<ymin>353</ymin>
			<xmax>950</xmax>
			<ymax>414</ymax>
		</bndbox>
	</object>
	<object>
		<name>COM_male</name>
		<pose>Unspecified</pose>
		<truncated>0</truncated>
		<difficult>0</difficult>
		<bndbox>
			<xmin>748</xmin>
			<ymin>336</ymin>
			<xmax>895</xmax>
			<ymax>428</ymax>
		</bndbox>
	</object>
	<object>
		<name>USB_2</name>
		<pose>Unspecified</pose>
		<truncated>0</truncated>
		<difficult>0</difficult>
		<bndbox>
			<xmin>958</xmin>
			<ymin>298</ymin>
			<xmax>1086</xmax>
			<ymax>369</ymax>
		</bndbox>
	</object>
	<object>
		<name>USB_2</name>
		<pose>Unspecified</pose>
		<truncated>0</truncated>
		<difficult>0</difficult>
		<bndbox>
			<xmin>958</xmin>
			<ymin>369</ymin>
			<xmax>1088</xmax>
			<ymax>438</ymax>
		</bndbox>
	</object>
	<object>
		<name>USB_3</name>
		<pose>Unspecified</pose>
		<truncated>0</truncated>
		<difficult>0</difficult>
		<bndbox>
			<xmin>1102</xmin>
			<ymin>302</ymin>
			<xmax>1231</xmax>
			<ymax>371</ymax>
		</bndbox>
	</object>
	<object>
		<name>USB_3</name>
		<pose>Unspecified</pose>
		<truncated>0</truncated>
		<difficult>0</difficult>
		<bndbox>
			<xmin>1102</xmin>
			<ymin>371</ymin>
			<xmax>1227</xmax>
			<ymax>438</ymax>
		</bndbox>
	</object>
	<object>
		<name>Ethernet</name>
		<pose>Unspecified</pose>
		<truncated>0</truncated>
		<difficult>0</difficult>
		<bndbox>
			<xmin>1238</xmin>
			<ymin>317</ymin>
			<xmax>1389</xmax>
			<ymax>450</ymax>
		</bndbox>
	</object>
	<object>
		<name>Ethernet</name>
		<pose>Unspecified</pose>
		<truncated>0</truncated>
		<difficult>0</difficult>
		<bndbox>
			<xmin>1393</xmin>
			<ymin>317</ymin>
			<xmax>1548</xmax>
			<ymax>453</ymax>
		</bndbox>
	</object>
	<object>
		<name>Schraube_abstand</name>
		<pose>Unspecified</pose>
		<truncated>0</truncated>
		<difficult>0</difficult>
		<bndbox>
			<xmin>1550</xmin>
			<ymin>350</ymin>
			<xmax>1612</xmax>
			<ymax>410</ymax>
		</bndbox>
	</object>
	<object>
		<name>Schraube_abstand</name>
		<pose>Unspecified</pose>
		<truncated>0</truncated>
		<difficult>0</difficult>
		<bndbox>
			<xmin>1758</xmin>
			<ymin>353</ymin>
			<xmax>1815</xmax>
			<ymax>412</ymax>
		</bndbox>
	</object>
	<object>
		<name>Powerstecker_off</name>
		<pose>Unspecified</pose>
		<truncated>0</truncated>
		<difficult>0</difficult>
		<bndbox>
			<xmin>1610</xmin>
			<ymin>341</ymin>
			<xmax>1757</xmax>
			<ymax>424</ymax>
		</bndbox>
	</object>
	<object>
		<name>LOGO_Kontron_icon</name>
		<pose>Unspecified</pose>
		<truncated>0</truncated>
		<difficult>0</difficult>
		<bndbox>
			<xmin>1765</xmin>
			<ymin>172</ymin>
			<xmax>1827</xmax>
			<ymax>241</ymax>
		</bndbox>
	</object>
	<object>
		<name>LOGO_Kontron_font</name>
		<pose>Unspecified</pose>
		<truncated>0</truncated>
		<difficult>0</difficult>
		<bndbox>
			<xmin>1572</xmin>
			<ymin>172</ymin>
			<xmax>1764</xmax>
			<ymax>234</ymax>
		</bndbox>
	</object>
	<object>
		<name>CamFront</name>
		<pose>Unspecified</pose>
		<truncated>1</truncated>
		<difficult>0</difficult>
		<bndbox>
			<xmin>202</xmin>
			<ymin>79</ymin>
			<xmax>1920</xmax>
			<ymax>598</ymax>
		</bndbox>
	</object>
	<object>
		<name>Schraube_gespiegelt</name>
		<pose>Unspecified</pose>
		<truncated>0</truncated>
		<difficult>0</difficult>
		<bndbox>
			<xmin>303</xmin>
			<ymin>609</ymin>
			<xmax>362</xmax>
			<ymax>693</ymax>
		</bndbox>
	</object>
	<object>
		<name>Schraube_gespiegelt</name>
		<pose>Unspecified</pose>
		<truncated>0</truncated>
		<difficult>0</difficult>
		<bndbox>
			<xmin>1772</xmin>
			<ymin>621</ymin>
			<xmax>1834</xmax>
			<ymax>710</ymax>
		</bndbox>
	</object>
	<object>
		<name>Schraube_gespiegelt</name>
		<pose>Unspecified</pose>
		<truncated>0</truncated>
		<difficult>0</difficult>
		<bndbox>
			<xmin>1789</xmin>
			<ymin>964</ymin>
			<xmax>1852</xmax>
			<ymax>1064</ymax>
		</bndbox>
	</object>
</annotation>
